fcp/__init__.py
fcp/__main__.py
fcp/codegen.py
fcp/colors.py
fcp/encoding.py
fcp/error.py
fcp/error_logger.py
fcp/maybe.py
fcp/result.py
fcp/serde.py
fcp/types.py
fcp/v2_parser.py
fcp/verifier.py
fcp/version.py
fcp/specs/__init__.py
fcp/specs/enum.py
fcp/specs/impl.py
fcp/specs/metadata.py
fcp/specs/rpc.py
fcp/specs/service.py
fcp/specs/signal_block.py
fcp/specs/struct.py
fcp/specs/struct_field.py
fcp/specs/type.py
fcp/specs/v2.py
fcp-1.0.0.dev1.dist-info/METADATA
fcp-1.0.0.dev1.dist-info/WHEEL
fcp-1.0.0.dev1.dist-info/entry_points.txt
fcp-1.0.0.dev1.dist-info/licenses/AUTHORS
fcp-1.0.0.dev1.dist-info/licenses/LICENSE
fcp-1.0.0.dev1.dist-info/RECORD
