Metadata-Version: 2.3
Name: fcp
Version: 1.0.0.dev1
Summary: CAN bus manager
License: MIT License
Requires-Python: >=3.8
Requires-Dist: click>=8.1.3
Requires-Dist: coloredlogs>=15.0.1
Requires-Dist: lark>=1.1.5
Requires-Dist: pyserde>=0.15.0
Requires-Dist: termcolor>=2.4.0
Provides-Extra: test
Requires-Dist: cantools; extra == 'test'
Requires-Dist: docutils; extra == 'test'
Requires-Dist: hypothesis; extra == 'test'
Requires-Dist: marko; extra == 'test'
Requires-Dist: pygments; extra == 'test'
Requires-Dist: pytest; extra == 'test'
